types_botocore/__init__.py
types_botocore/py.typed
types_botocore-1.0.2.dist-info/LICENSE
types_botocore-1.0.2.dist-info/METADATA
types_botocore-1.0.2.dist-info/WHEEL
types_botocore-1.0.2.dist-info/top_level.txt
types_botocore-1.0.2.dist-info/RECORD
