Metadata-Version: 2.1
Name: types-botocore
Version: 1.0.2
Summary: Proxy package for botocore-stubs
Home-page: https://github.com/youtype/mypy_boto3_builder
Author: Vlad Emelianov
Author-email: vlad.emelianov.nz@gmail.com
License: MIT
Project-URL: Documentation, https://mypy-boto3-builder.readthedocs.io/en/latest/
Project-URL: Source, https://github.com/youtype/mypy_boto3_builder
Project-URL: Tracker, https://github.com/youtype/mypy_boto3_builder/issues
Keywords: boto3 type-annotations pyright mypy boto3-stubs
Platform: any
Classifier: Development Status :: 5 - Production/Stable
Classifier: Environment :: Console
Classifier: License :: OSI Approved :: MIT License
Classifier: Natural Language :: English
Classifier: Operating System :: OS Independent
Classifier: Programming Language :: Python :: 3
Classifier: Programming Language :: Python :: 3.8
Classifier: Programming Language :: Python :: 3.9
Classifier: Programming Language :: Python :: 3 :: Only
Classifier: Programming Language :: Python :: Implementation :: CPython
Classifier: Typing :: Typed
Classifier: Topic :: Software Development :: Libraries :: Python Modules
License-File: LICENSE
